qtext/__init__.py
qtext/client.py
qtext/config.py
qtext/emb_client.py
qtext/engine.py
qtext/highlight_client.py
qtext/log.py
qtext/main.py
qtext/metrics.py
qtext/pg_client.py
qtext/ranker.py
qtext/schema.py
qtext/server.py
qtext/spec.py
qtext/utils.py
qtext-0.1.0.dist-info/LICENSE
qtext-0.1.0.dist-info/METADATA
qtext-0.1.0.dist-info/WHEEL
qtext-0.1.0.dist-info/entry_points.txt
qtext-0.1.0.dist-info/top_level.txt
qtext-0.1.0.dist-info/RECORD
