Metadata-Version: 2.1
Name: qtext
Version: 0.1.0
Summary: Query the text with keywords, vector similarity and other attributes.
Author-email: Keming <kemingy94@gmail.com>
License: Apache-2.0
Project-URL: Homepage, https://github.com/kemingy/qtext
Classifier: Intended Audience :: Developers
Requires-Python: >=3.8
License-File: LICENSE
Requires-Dist: msgspec ~=0.18.6
Requires-Dist: falcon ~=3.1.1
Requires-Dist: waitress ~=3.0.0
Requires-Dist: psycopg[binary] ~=3.1
Requires-Dist: openai ~=1.12.0
Requires-Dist: defspec ~=0.1.1
Requires-Dist: httpx ~=0.27
Requires-Dist: cohere ~=4.45
Requires-Dist: prometheus-client ~=0.20
Requires-Dist: numpy ~=1.26
Provides-Extra: dev
Requires-Dist: ruff ~=0.2.2 ; extra == 'dev'
Requires-Dist: pytest ~=7.4 ; extra == 'dev'
